opensearch_kb_mcp_server/__init__.py
opensearch_kb_mcp_server/server.py
opensearch_knowledge_base_mcp_server-1.0.0.dist-info/METADATA
opensearch_knowledge_base_mcp_server-1.0.0.dist-info/WHEEL
opensearch_knowledge_base_mcp_server-1.0.0.dist-info/entry_points.txt
opensearch_knowledge_base_mcp_server-1.0.0.dist-info/licenses/LICENSE
opensearch_knowledge_base_mcp_server-1.0.0.dist-info/RECORD
