Metadata-Version: 2.4
Name: opensearch-knowledge-base-mcp-server
Version: 1.0.0
Summary: MCP server for OpenSearch Knowledge Base - Search OpenSearch best practices and documentation from any AI agent
Project-URL: Homepage, https://github.com/your-org/opensearch-knowledge-base-mcp
Project-URL: Documentation, https://github.com/your-org/opensearch-knowledge-base-mcp/blob/main/docs/MCP_SERVER_GUIDE.md
Project-URL: Repository, https://github.com/your-org/opensearch-knowledge-base-mcp
Project-URL: Issues, https://github.com/your-org/opensearch-knowledge-base-mcp/issues
Author-email: OpenSearch MCP Team <contact@example.com>
License: MIT
License-File: LICENSE
Keywords: agent,ai,claude,knowledge-base,llm,mcp,opensearch
Classifier: Development Status :: 4 - Beta
Classifier: Intended Audience :: Developers
Classifier: License :: OSI Approved :: MIT License
Classifier: Programming Language :: Python :: 3
Classifier: Programming Language :: Python :: 3.10
Classifier: Programming Language :: Python :: 3.11
Classifier: Programming Language :: Python :: 3.12
Classifier: Topic :: Scientific/Engineering :: Artificial Intelligence
Classifier: Topic :: Software Development :: Libraries :: Python Modules
Requires-Python: >=3.10
Requires-Dist: httpx>=0.27.0
Requires-Dist: mcp>=1.0.0
